sklearn_rvm/__init__.py
sklearn_rvm/_template.py
sklearn_rvm/_version.py
sklearn_rvm/em_rvm.py
sklearn_rvm/example4.py
sklearn_rvm/playground.py
sklearn_rvm/playground2.py
sklearn_rvm/playground3.py
sklearn_rvm/rvc_em.py
sklearn_rvm/rvm.py
sklearn_rvm/tests/__init__.py
sklearn_rvm/tests/performance.py
sklearn_rvm/tests/test_classifier.py
sklearn_rvm/tests/test_common.py
sklearn_rvm/tests/test_regressor.py
sklearn_rvm/tests/test_template.py
sklearn_rvm-0.1.1.dist-info/AUTHORS.rst
sklearn_rvm-0.1.1.dist-info/LICENSE
sklearn_rvm-0.1.1.dist-info/METADATA
sklearn_rvm-0.1.1.dist-info/WHEEL
sklearn_rvm-0.1.1.dist-info/top_level.txt
sklearn_rvm-0.1.1.dist-info/RECORD
