Metadata-Version: 2.1
Name: sklearn_rvm
Version: 0.1.1
Summary: An scikit-learn style implementation of Relevance Vector Machines (RVM).
Home-page: https://github.com/Mind-the-Pineapple/sklearn-rvm
Maintainer: Pedro F. da Costa, Walter Hugo Lopez Pinaya
Maintainer-email: pedro.ferreira_da_costa@kcl.ac.uk, walter.diaz_sanz@kcl.ac.uk
License: new BSD
Download-URL: https://github.com/Mind-the-Pineapple/sklearn-rvm
Platform: UNKNOWN
Classifier: Intended Audience :: Science/Research
Classifier: Intended Audience :: Developers
Classifier: License :: OSI Approved
Classifier: Programming Language :: Python
Classifier: Topic :: Software Development
Classifier: Topic :: Scientific/Engineering
Classifier: Operating System :: Microsoft :: Windows
Classifier: Operating System :: POSIX
Classifier: Operating System :: Unix
Classifier: Operating System :: MacOS
Classifier: Programming Language :: Python :: 3.5
Classifier: Programming Language :: Python :: 3.6
Classifier: Programming Language :: Python :: 3.7
Provides-Extra: tests
Provides-Extra: docs
